pypowhegparse/__init__.py
pypowhegparse/checklimits.py
pypowhegparse/counters.py
pypowhegparse/interactive.py
pypowhegparse/pypowhegparse.py
pypowhegparse/stat.py
pypowhegparse/top.py
pypowhegparse/util.py
pypowhegparse-0.0.4.dist-info/METADATA
pypowhegparse-0.0.4.dist-info/WHEEL
pypowhegparse-0.0.4.dist-info/entry_points.txt
pypowhegparse-0.0.4.dist-info/RECORD
